simages/__init__.py
simages/dataset.py
simages/embeddings.py
simages/extractor.py
simages/main.py
simages/models.py
simages/duplicate_images/.gitignore
simages/duplicate_images/__init__.py
simages/duplicate_images/duplicate_finder.py
simages/duplicate_images/requirements-test.txt
simages/duplicate_images/requirements.txt
simages/duplicate_images/template/index.html
simages/duplicate_images/tests/__init__.py
simages/duplicate_images/tests/test.py
simages/duplicate_images/tests/images/file.gif
simages/duplicate_images/tests/images/file.png
simages/duplicate_images/tests/images/file.tiff
simages/duplicate_images/tests/images/image.txt
simages/duplicate_images/tests/images/not_image.jpg
simages/duplicate_images/tests/images/not_image.txt
simages/duplicate_images/tests/images/u.jpg
simages/duplicate_images/tests/images/deeply/nested/different.jpg
simages/duplicate_images/tests/images/deeply/nested/image/sideways.jpg
simages/duplicate_images/tests/images/deeply/nested/image/smaller.jpg
simages-23.0.7.dist-info/AUTHORS.rst
simages-23.0.7.dist-info/LICENSE
simages-23.0.7.dist-info/METADATA
simages-23.0.7.dist-info/WHEEL
simages-23.0.7.dist-info/entry_points.txt
simages-23.0.7.dist-info/top_level.txt
simages-23.0.7.dist-info/RECORD
