Metadata-Version: 2.1
Name: simages
Version: 23.0.7
Summary: Find similar images in a dataset
Home-page: https://github.com/justinshenk/simages
Author: Justin Shenk
Author-email: shenkjustin@gmail.com
Maintainer: Justin Shenk
Maintainer-email: shenkjustin@gmail.com
License: MIT
Keywords: images,photos,duplicates,preprocessing,similar data
Classifier: Intended Audience :: Developers
Classifier: License :: OSI Approved :: MIT License
Classifier: Intended Audience :: Education
Classifier: Intended Audience :: Science/Research
Classifier: Programming Language :: Python :: 3
Classifier: Programming Language :: Python :: 3.6
Classifier: Topic :: Scientific/Engineering :: Mathematics
Classifier: Topic :: Software Development :: Libraries :: Python Modules
Classifier: Topic :: Software Development :: Libraries
Requires-Python: >= 3.6
License-File: LICENSE
License-File: AUTHORS.rst
Requires-Dist: numpy
Requires-Dist: scipy
Requires-Dist: torch (>=1.0)
Requires-Dist: torchvision (>=0.3)
Requires-Dist: Pillow
Requires-Dist: closely
Requires-Dist: flask
Requires-Dist: jinja2 (>=2.10)
Requires-Dist: more-itertools
Requires-Dist: pymongo (==3.7.0)
Requires-Dist: bokeh
Requires-Dist: Flask-Cors
Requires-Dist: dnspython
Requires-Dist: Werkzeug
Requires-Dist: python-magic
Requires-Dist: termcolor
Requires-Dist: scikit-learn
Provides-Extra: dev
Requires-Dist: coverage ; extra == 'dev'
Requires-Dist: pytest ; extra == 'dev'
Requires-Dist: sphinx ; extra == 'dev'
Requires-Dist: wheel ; extra == 'dev'
Requires-Dist: pre-commit ; extra == 'dev'
Provides-Extra: docs
Requires-Dist: sphinx ; extra == 'docs'
Provides-Extra: tests
Requires-Dist: coverage ; extra == 'tests'
Requires-Dist: pytest ; extra == 'tests'
